HISTORY.txt
LICENSE
MANIFEST.in
README.md
setup.py
wendy/__init__.py
wendy/bst.c
wendy/bst.h
wendy/parallel_sort.c
wendy/parallel_sort.h
wendy/sort.h
wendy/wendy.c
wendy/wendy.h
wendy/wendy.py
wendy.egg-info/PKG-INFO
wendy.egg-info/SOURCES.txt
wendy.egg-info/dependency_links.txt
wendy.egg-info/requires.txt
wendy.egg-info/top_level.txt