Metadata-Version: 2.1
Name: wendy
Version: 0.2
Summary: One-dimensional gravitational N-body code
Home-page: http://github.com/jobovy/wendy
Author: Jo Bovy
Author-email: bovy@astro.utoronto.ca
License: MIT
Platform: UNKNOWN
